thumbor_padding-1.0.0.dist-info/METADATA
thumbor_padding-1.0.0.dist-info/RECORD
thumbor_padding-1.0.0.dist-info/WHEEL
thumbor_padding-1.0.0.dist-info/top_level.txt
thumbor_padding_filter/__init__.py
thumbor_padding_filter/padding.py
