Metadata-Version: 2.1
Name: thumbor-padding
Version: 1.0.0
Summary: Padding filter for thumbor.
Home-page: https://github.com/arcivr/thumbor-padding
Author: Derek Lucas
Author-email: derek.lucas@arcivr.com
License: MIT
Keywords: thumbor filter
Platform: UNKNOWN
Classifier: Development Status :: 4 - Beta
Classifier: Intended Audience :: Developers
Classifier: License :: OSI Approved :: MIT License
Classifier: Natural Language :: English
Classifier: Operating System :: MacOS
Classifier: Operating System :: POSIX
Classifier: Operating System :: Unix
Classifier: Operating System :: OS Independent
Classifier: Programming Language :: Python :: 2.7
Provides-Extra: tests
Requires-Dist: pillow
Provides-Extra: tests
Requires-Dist: mock; extra == 'tests'
Requires-Dist: nose; extra == 'tests'
Requires-Dist: coverage; extra == 'tests'
Requires-Dist: yanc; extra == 'tests'
Requires-Dist: colorama; extra == 'tests'
Requires-Dist: preggy; extra == 'tests'
Requires-Dist: ipdb; extra == 'tests'
Requires-Dist: coveralls; extra == 'tests'
Requires-Dist: numpy; extra == 'tests'
